twitch/__init__.py
twitch/api.py
twitch/app.py
twitch/errors.py
twitch/http.py
twitch/models.py
twitch/py.typed
twitch/state.py
twitch/utils.py
twitch/eventsub/__init__.py
twitch/eventsub/client.py
twitch/eventsub/errors.py
twitch/eventsub/event.py
twitch/eventsub/gateway.py
twitch/eventsub/models.py
twitch/eventsub/shard.py
twitch/ext/tasks/__init__.py
twitch/oauth/__init__.py
twitch/oauth/flows.py
twitch/oauth/models.py
twitch/oauth/scopes.py
twitch/types/__init__.py
twitch/types/eventsub.py
twitch/types/helix.py
twitch/types/tokens.py
twitch_py-4.0.3.dist-info/LICENSE
twitch_py-4.0.3.dist-info/METADATA
twitch_py-4.0.3.dist-info/WHEEL
twitch_py-4.0.3.dist-info/top_level.txt
twitch_py-4.0.3.dist-info/RECORD
