Metadata-Version: 2.1
Name: twitch.py
Version: 4.0.3
Summary: Async Python wrapper for Twitch EventSub and Helix API
Author-email: Snifo <Snifo@mail.com>
License: MIT
Project-URL: Homepage, https://github.com/mrsnifo/twitch.py
Project-URL: Documentation, https://twitchpy.readthedocs.io/latest/
Project-URL: Repository, https://github.com/mrsnifo/twitch.py
Project-URL: Issue tracker, https://github.com/mrsnifo/twitch.py/issues
Project-URL: Discord, https://discord.gg/UFTkgnse7d
Keywords: twitch,api,eventsub,websocket,helix,conduit
Classifier: Development Status :: 5 - Production/Stable
Classifier: License :: OSI Approved :: MIT License
Classifier: Intended Audience :: Developers
Classifier: Operating System :: OS Independent
Classifier: Programming Language :: Python :: 3.11
Classifier: Programming Language :: Python :: 3.12
Classifier: Programming Language :: Python :: 3.13
Classifier: Topic :: Software Development :: Libraries :: Python Modules
Classifier: Framework :: AsyncIO
Requires-Python: <4.0,>=3.11.0
License-File: LICENSE
Requires-Dist: aiohttp <4.0,>=3.10.6
Provides-Extra: docs
Requires-Dist: mkdocs-material ==9.6.16 ; extra == 'docs'
Requires-Dist: mkdocstrings-python ==1.17.0 ; extra == 'docs'
